<annotation>
	<folder>negatifPhoto</folder>
	<filename>flower_0629.jpg</filename>
	<path>C:\Users\Ebruarslan\Desktop\negatifPhoto\flower_0629.jpg</path>
	<source>
		<database>Unknown</database>
	</source>
	<size>
		<width>226</width>
		<height>251</height>
		<depth>3</depth>
	</size>
	<segmented>0</segmented>
	<object>
		<name>copdegil</name>
		<pose>Unspecified</pose>
		<truncated>0</truncated>
		<difficult>0</difficult>
		<bndbox>
			<xmin>8</xmin>
			<ymin>2</ymin>
			<xmax>225</xmax>
			<ymax>239</ymax>
		</bndbox>
	</object>
</annotation>
